bleach/__init__.py
bleach/callbacks.py
bleach/css_sanitizer.py
bleach/html5lib_shim.py
bleach/linkifier.py
bleach/sanitizer.py
bleach/_vendor/README.rst
bleach/_vendor/__init__.py
bleach/_vendor/parse.py
bleach/_vendor/parse.py.SHA256SUM
bleach/_vendor/vendor.txt
bleach/_vendor/vendor_install.sh
bleach/_vendor/html5lib/__init__.py
bleach/_vendor/html5lib/_ihatexml.py
bleach/_vendor/html5lib/_inputstream.py
bleach/_vendor/html5lib/_tokenizer.py
bleach/_vendor/html5lib/_utils.py
bleach/_vendor/html5lib/constants.py
bleach/_vendor/html5lib/html5parser.py
bleach/_vendor/html5lib/serializer.py
bleach/_vendor/html5lib/_trie/__init__.py
bleach/_vendor/html5lib/_trie/_base.py
bleach/_vendor/html5lib/_trie/py.py
bleach/_vendor/html5lib/filters/__init__.py
bleach/_vendor/html5lib/filters/alphabeticalattributes.py
bleach/_vendor/html5lib/filters/base.py
bleach/_vendor/html5lib/filters/inject_meta_charset.py
bleach/_vendor/html5lib/filters/lint.py
bleach/_vendor/html5lib/filters/optionaltags.py
bleach/_vendor/html5lib/filters/sanitizer.py
bleach/_vendor/html5lib/filters/whitespace.py
bleach/_vendor/html5lib/treeadapters/__init__.py
bleach/_vendor/html5lib/treeadapters/genshi.py
bleach/_vendor/html5lib/treeadapters/sax.py
bleach/_vendor/html5lib/treebuilders/__init__.py
bleach/_vendor/html5lib/treebuilders/base.py
bleach/_vendor/html5lib/treebuilders/dom.py
bleach/_vendor/html5lib/treebuilders/etree.py
bleach/_vendor/html5lib/treebuilders/etree_lxml.py
bleach/_vendor/html5lib/treewalkers/__init__.py
bleach/_vendor/html5lib/treewalkers/base.py
bleach/_vendor/html5lib/treewalkers/dom.py
bleach/_vendor/html5lib/treewalkers/etree.py
bleach/_vendor/html5lib/treewalkers/etree_lxml.py
bleach/_vendor/html5lib/treewalkers/genshi.py
bleach-5.0.0.dist-info/LICENSE
bleach-5.0.0.dist-info/METADATA
bleach-5.0.0.dist-info/WHEEL
bleach-5.0.0.dist-info/top_level.txt
bleach/_vendor/html5lib-1.1.dist-info/AUTHORS.rst
bleach/_vendor/html5lib-1.1.dist-info/INSTALLER
bleach/_vendor/html5lib-1.1.dist-info/LICENSE
bleach/_vendor/html5lib-1.1.dist-info/METADATA
bleach/_vendor/html5lib-1.1.dist-info/RECORD
bleach/_vendor/html5lib-1.1.dist-info/REQUESTED
bleach/_vendor/html5lib-1.1.dist-info/WHEEL
bleach/_vendor/html5lib-1.1.dist-info/top_level.txt
bleach-5.0.0.dist-info/RECORD
